Metadata-Version: 1.2
Name: tox-local-hooks
Version: 0.1.3
Summary: Write hooks for tox in a local file
Home-page: https://github.com/nizar-m/tox-local-hooks
Author: Nizar Malangadan
License: UNKNOWN
Platform: UNKNOWN
Classifier: Development Status :: 3 - Alpha
Classifier: Intended Audience :: Developers
Classifier: License :: OSI Approved :: Apache Software License
Classifier: Operating System :: POSIX
Classifier: Topic :: Software Development :: Testing
Classifier: Topic :: Software Development :: Libraries
Classifier: Topic :: Utilities
Classifier: Programming Language :: Python
Requires-Python: >3.5
